imgviz/__init__.py
imgviz/centerize.py
imgviz/color.py
imgviz/depth.py
imgviz/dtype.py
imgviz/flow.py
imgviz/instances.py
imgviz/label.py
imgviz/nchannel.py
imgviz/normalize.py
imgviz/resize.py
imgviz/tile.py
imgviz/trajectory.py
imgviz/utils.py
imgviz/_io/__init__.py
imgviz/_io/base.py
imgviz/_io/opencv.py
imgviz/_io/pil.py
imgviz/_io/pyplot.py
imgviz/_io/_pyglet/__init__.py
imgviz/_io/_pyglet/base.py
imgviz/_io/_pyglet/pyglet_imshow.py
imgviz/_io/_pyglet/pyglet_run.py
imgviz/data/__init__.py
imgviz/data/arc2017/__init__.py
imgviz/data/arc2017/camera_info.yaml
imgviz/data/arc2017/class_names.txt
imgviz/data/arc2017/data.npz
imgviz/data/arc2017/res4.npz
imgviz/data/arc2017/rgb.jpg
imgviz/data/kitti/__init__.py
imgviz/data/kitti/odometry/00.txt
imgviz/data/lena/__init__.py
imgviz/data/lena/lena.png
imgviz/data/middlebury/__init__.py
imgviz/data/middlebury/grove3.flo
imgviz/data/middlebury/grove3.png
imgviz/data/voc/__init__.py
imgviz/data/voc/class_names.txt
imgviz/data/voc/data.npz
imgviz/data/voc/rgb.jpg
imgviz/draw/__init__.py
imgviz/draw/circle.py
imgviz/draw/ellipse.py
imgviz/draw/line.py
imgviz/draw/rectangle.py
imgviz/draw/star.py
imgviz/draw/text.py
imgviz/draw/text_in_rectangle.py
imgviz/draw/triangle.py
imgviz/external/__init__.py
imgviz/external/transformations.py
imgviz-1.7.4.dist-info/LICENSE
imgviz-1.7.4.dist-info/METADATA
imgviz-1.7.4.dist-info/WHEEL
imgviz-1.7.4.dist-info/top_level.txt
imgviz-1.7.4.dist-info/RECORD
