Metadata-Version: 2.1
Name: imgviz
Version: 1.7.4
Summary: Image Visualization Tools
Home-page: http://github.com/wkentaro/imgviz
Author: Kentaro Wada
Author-email: www.kentaro.wada@gmail.com
License: MIT
Classifier: Development Status :: 5 - Production/Stable
Classifier: Intended Audience :: Developers
Classifier: License :: OSI Approved :: MIT License
Classifier: Operating System :: OS Independent
Classifier: Programming Language :: Python
Classifier: Programming Language :: Python :: 3.5
Classifier: Programming Language :: Python :: 3.6
Classifier: Programming Language :: Python :: 3.7
Classifier: Programming Language :: Python :: 3.8
Classifier: Programming Language :: Python :: 3.9
Classifier: Programming Language :: Python :: 3.10
Requires-Python: >=3.5
Provides-Extra: all
License-File: LICENSE
